{
	"class" : {
		"hasInterface" : "tm 8/4/2015 18:03",
		"initialize" : "tm 8/4/2015 18:03",
		"interface" : "tm 8/4/2015 18:03",
		"interface:" : "tm 8/4/2015 18:03",
		"interfaceClass" : "tm 8/4/2015 18:03",
		"isPortRequested" : "tm 8/4/2015 18:03",
		"isReplRequested" : "tm 8/4/2015 18:03",
		"new" : "tm 8/4/2015 18:03",
		"port" : "tm 8/4/2015 18:03",
		"portArgument" : "tm 8/4/2015 18:03",
		"replArgument" : "tm 8/4/2015 18:03",
		"shutDown:" : "tm 8/4/2015 18:03",
		"startUp:" : "tm 8/4/2015 18:03" },
	"instance" : {
		 } }
